file_management_package/__init__.py
file_management_package/file_manager.py
file_management_package-0.8.1.dist-info/LICENSE
file_management_package-0.8.1.dist-info/METADATA
file_management_package-0.8.1.dist-info/WHEEL
file_management_package-0.8.1.dist-info/top_level.txt
file_management_package-0.8.1.dist-info/RECORD
