Metadata-Version: 2.1
Name: file-management-package
Version: 0.8.1
Summary: A package for file management
Home-page: https://github.com/Pascal-Benink/File-Management-Package
Author: Pascal Benink
Author-email: 2sam2samb+PythonFile@gmail.com
Classifier: Programming Language :: Python :: 3
Classifier: License :: OSI Approved :: MIT License
Classifier: Operating System :: OS Independent
Requires-Python: >=3.10.12
License-File: LICENSE
Requires-Dist: setuptools
